datadict_cli/__init__.py
datadict_cli/__main__.py
datadict_cli/cli.py
datadict_cli/commands/__init__.py
datadict_cli/commands/build.py
datadict_cli/commands/catalog.py
datadict_cli/commands/info.py
datadict_cli/commands/init.py
datadict_cli/commands/preview.py
datadict_cli/commands/pull.py
datadict_cli/lib/__init__.py
datadict_cli/lib/apply.py
datadict_cli/lib/catalog.py
datadict_cli/lib/constants.py
datadict_cli/lib/context.py
datadict_cli/lib/item.py
datadict_cli/lib/lineage.py
datadict_cli/lib/loader.py
datadict_cli/lib/models.py
datadict_cli/lib/paths.py
datadict_cli/lib/project.py
datadict_cli/lib/queries.py
datadict_cli/lib/schemas.py
datadict_cli/lib/sync.py
datadict_cli/lib/types.py
datadict_cli/lib/preview/__init__.py
datadict_cli/lib/preview/endpoints.py
datadict_cli/lib/preview/server.py
datadict_cli/lib/preview/static/__init__.py
datadict_cli/lib/preview/static/favicon.ico
datadict_cli/lib/preview/static/index.html
datadict_cli/lib/serializer/__init__.py
datadict_cli/lib/serializer/api_schemas.py
datadict_cli/lib/serializer/serializer.py
datadict_cli/util/__init__.py
datadict_cli/util/common.py
datadict_cli/util/db.py
datadict_cli/util/logger.py
datadict_cli-0.0.2.dist-info/licenses/LICENSE
lib/__init__.py
lib/preview/__init__.py
lib/preview/endpoints.py
lib/preview/server.py
datadict_cli-0.0.2.dist-info/METADATA
datadict_cli-0.0.2.dist-info/WHEEL
datadict_cli-0.0.2.dist-info/entry_points.txt
datadict_cli-0.0.2.dist-info/top_level.txt
datadict_cli-0.0.2.dist-info/RECORD
